{
  "system": {
    "keymanDeveloperVersion": "10.0.1206.0",
    "fileVersion": "7.0"
  },
  "options": {
    "readmeFile": "readme.html",
    "graphicFile": "Malayalam_Swanalekha_Image.png"
  },
  "info": {
    "version": {
      "description": "1.1.0"
    },
    "name": {
      "description": "Malayalam Swanalekha"
    },
    "copyright": {
      "description": "MIT License"
    },
    "author": {
      "description": "Ramesh Kunnappully",
      "url": "mailto:ramesh1@protonmail.com"
    },
    "website": {
      "description": ""
    }
  },
  "files": [
    {
      "name": "Malayalam_Swanalekha.kmx",
      "description": "Keyboard Malayalam Swanalekha"
    },
    {
      "name": "readme.html",
      "description": "File readme.html"
    },
    {
      "name": "Malayalam_Swanalekha_Image.png",
      "description": "File Malayalam_Swanalekha_Image.png"
    },
    {
      "name": "kmp.inf",
      "description": "Package information"
    },
    {
      "name": "kmp.json",
      "description": "Package information (JSON)"
    }
  ],
  "keyboards": [
    {
      "name": "Malayalam Swanalekha",
      "id": "malayalam_swanalekha",
      "version": "1.1.0",
      "languages": [
        {
          "name": "Malayalam",
          "id": "ml"
        }
      ]
    }
  ]
}
